owlrl/AxiomaticTriples.py
owlrl/Closure.py
owlrl/CombinedClosure.py
owlrl/DatatypeHandling.py
owlrl/Namespaces.py
owlrl/OWLRL.py
owlrl/OWLRLExtras.py
owlrl/RDFSClosure.py
owlrl/RestrictedDatatype.py
owlrl/XsdDatatypes.py
owlrl/__init__.py
owlrl-7.1.2.dist-info/LICENSE.txt
owlrl-7.1.2.dist-info/WHEEL
owlrl-7.1.2.dist-info/METADATA
owlrl-7.1.2.dist-info/RECORD
