Metadata-Version: 2.1
Name: owlrl
Version: 7.1.2
Summary: A simple implementation of the OWL2 RL Profile, as well as a basic RDFS inference, on top of RDFLib. Based mechanical forward chaining.
License: W3C software and Document Notice License
Author: Nicholas Car
Author-email: nick@kurrawong.ai
Requires-Python: >=3.8,<4.0
Classifier: License :: Other/Proprietary License
Classifier: Programming Language :: Python :: 3
Classifier: Programming Language :: Python :: 3.8
Classifier: Programming Language :: Python :: 3.9
Classifier: Programming Language :: Python :: 3.10
Classifier: Programming Language :: Python :: 3.11
Requires-Dist: rdflib (>=7.1.1)
